naucse/__init__.py
naucse/__main__.py
naucse/cli.py
naucse/compiled_renderer.py
naucse/converters.py
naucse/datetimes.py
naucse/edit_info.py
naucse/exceptions.py
naucse/local_renderer.py
naucse/logger.py
naucse/models.py
naucse/sanitize.py
naucse/templates.py
naucse/urlconverters.py
naucse/views.py
naucse/licenses/cc-by-sa-40/info.yml
naucse/licenses/cc0/info.yml
naucse/static/pycon2016cz.png
naucse/static/css/body.css
naucse/static/css/bootstrap.css
naucse/static/css/calendar.css
naucse/static/css/index.css
naucse/static/css/ipython.css
naucse/static/css/naucse.css
naucse/static/css/pygments-lovelace-style.css
naucse/static/css/reveal-theme.css
naucse/static/css/reveal-theme.scss
naucse/static/js/solutions.js
naucse/static/js/start_reveal.js
naucse/templates/_base.html
naucse/templates/_base_course.html
naucse/templates/_bytesize_icons.html
naucse/templates/_course_list.html
naucse/templates/_material_macros.html
naucse/templates/_navigation_macros.html
naucse/templates/backpage.html
naucse/templates/course.html
naucse/templates/course_calendar.html
naucse/templates/course_list.html
naucse/templates/coverpage.html
naucse/templates/dev_course_list.html
naucse/templates/index.html
naucse/templates/lesson.html
naucse/templates/run_list.html
naucse-0.5.3.dist-info/LICENSE.MIT
naucse-0.5.3.dist-info/METADATA
naucse-0.5.3.dist-info/WHEEL
naucse-0.5.3.dist-info/top_level.txt
naucse-0.5.3.dist-info/RECORD
