Metadata-Version: 2.1
Name: naucse
Version: 0.5.3
Summary: Website for course materials
Author: naucse.python.cz contributors
Author-email: Petr Viktorin <encukou@gmail.com>
License: The MIT License (MIT)
Project-URL: home, https://github.com/pyvec/naucse
Project-URL: changelog, https://github.com/pyvec/naucse/blob/master/CHANGELOG.md
License-File: LICENSE.MIT
Requires-Dist: elsa
Requires-Dist: ics
Requires-Dist: cssutils
Requires-Dist: PyYAML
Requires-Dist: Flask
Requires-Dist: Jinja2
Requires-Dist: Werkzeug (>=2.2.0)
Requires-Dist: jsonschema
Requires-Dist: lxml
Requires-Dist: naucse-render (>=1.7)
Requires-Dist: markupsafe
Requires-Dist: gitpathlib
Requires-Dist: backports.zoneinfo ; python_version < "3.9"
Requires-Dist: tzdata ; sys_platform == "win32"
Provides-Extra: dev
Requires-Dist: tox ; extra == 'dev'
Requires-Dist: pytest ; extra == 'dev'
Requires-Dist: hypothesis ; extra == 'dev'
Provides-Extra: test
Requires-Dist: pytest ; extra == 'test'
Requires-Dist: hypothesis ; extra == 'test'
